MKE_M17/L9110_I2C.py
MKE_M17/__init__.py
mke_m17-25.3.13.1.dist-info/LICENSE
mke_m17-25.3.13.1.dist-info/METADATA
mke_m17-25.3.13.1.dist-info/WHEEL
mke_m17-25.3.13.1.dist-info/top_level.txt
mke_m17-25.3.13.1.dist-info/RECORD
