Metadata-Version: 2.2
Name: MKE_M17
Version: 25.3.13.1
Summary: A package for controlling JetRacer
Author-email: Quy-An <quyan18b@gmail.com>
Requires-Python: >=3.11
License-File: LICENSE
Requires-Dist: smbus>=1.1.post2
